normalurl.py
normalurl-1.0.1.dist-info/WHEEL
normalurl-1.0.1.dist-info/METADATA
normalurl-1.0.1.dist-info/RECORD
