Metadata-Version: 2.4
Name: normalurl
Version: 1.0.1
Summary: Convenient utility to parse and normalize urls.
Author-email: baterflyrity <baterflyrity@yandex.ru>
Project-URL: Home, https://github.com/baterflyrity/normalurl
Project-URL: Issues, https://github.com/baterflyrity/normalurl/issues
